qepseudos
