Metadata-Version: 2.1
Name: qepseudos
Version: 0.0.4
Summary: Pseudo potentials for QuantumEspresso calculations
Home-page: UNKNOWN
Author: Harish PVV
Author-email: harishpvv@gmail.com
License: MIT
Keywords: quantum espresso pseudo potentials dft harishpvv
Platform: UNKNOWN
Classifier: Programming Language :: Python :: 3
Classifier: License :: OSI Approved :: MIT License
Classifier: Operating System :: OS Independent
Requires-Python: >=3.6
License-File: LICENCE
